orac/__init__.py
orac/_meta.py
orac/cli.py
orac/client.py
orac/config.py
orac/config.yaml
orac/llm.py
orac/logger.py
orac/orac.py
orac/prompts/capital.yaml
orac/prompts/paper2audio.yaml
orac/prompts/recipe.yaml
orac-0.1.1.dist-info/LICENSE
orac-0.1.1.dist-info/METADATA
orac-0.1.1.dist-info/WHEEL
orac-0.1.1.dist-info/entry_points.txt
orac-0.1.1.dist-info/top_level.txt
orac-0.1.1.dist-info/RECORD
