Metadata-Version: 2.1
Name: orac
Version: 0.1.1
Summary: A lightweight, YAML-driven framework for OpenAI-compatible LLM APIs.
Home-page: https://github.com/phil/orac
Author: Philip Orange
Author-email: git@philiporange.com
License: MIT
Requires-Python: >=3.9
License-File: LICENSE
Requires-Dist: PyYAML >=6.0
Requires-Dist: google-generativeai <1,>=0.3.0
Requires-Dist: loguru >=0.7.2
Requires-Dist: openai >=1.23.0
Requires-Dist: python-dotenv >=1.0.0
Provides-Extra: dev
Requires-Dist: pytest >=8.2 ; extra == 'dev'
Requires-Dist: ruff >=0.4.0 ; extra == 'dev'
